hashr/__init__.py
hashr/main.py
hashr-1.0.0.dist-info/LICENSE
hashr-1.0.0.dist-info/METADATA
hashr-1.0.0.dist-info/WHEEL
hashr-1.0.0.dist-info/entry_points.txt
hashr-1.0.0.dist-info/top_level.txt
hashr-1.0.0.dist-info/RECORD
