Metadata-Version: 2.1
Name: hashr
Version: 1.0.0
Summary: Custom hash function for Python
Author: Lucas Hill
Classifier: Programming Language :: Python :: 3
Classifier: License :: OSI Approved :: MIT License
Classifier: Operating System :: OS Independent
Requires-Python: >=3.6
License-File: LICENSE
